tools.py
detlfy-0.0.1.dist-info/METADATA
detlfy-0.0.1.dist-info/WHEEL
detlfy-0.0.1.dist-info/top_level.txt
detlfy-0.0.1.dist-info/RECORD
