Metadata-Version: 2.1
Name: detlfy
Version: 0.0.1
Summary: some tools~
Home-page: UNKNOWN
Author: DetLFY
Author-email: 1833023508@qq.com
License: UNKNOWN
Platform: UNKNOWN
